adafruit_vl53l0x.py
adafruit_circuitpython_vl53l0x-3.6.15.dist-info/licenses/LICENSE
adafruit_circuitpython_vl53l0x-3.6.15.dist-info/METADATA
adafruit_circuitpython_vl53l0x-3.6.15.dist-info/WHEEL
adafruit_circuitpython_vl53l0x-3.6.15.dist-info/top_level.txt
adafruit_circuitpython_vl53l0x-3.6.15.dist-info/RECORD
